antchain_sdk_ak_c810f9cbf799426aa25d207ce46b7566/__init__.py
antchain_sdk_ak_c810f9cbf799426aa25d207ce46b7566/client.py
antchain_sdk_ak_c810f9cbf799426aa25d207ce46b7566/models.py
antchain_ak_c810f9cbf799426aa25d207ce46b7566-1.0.0.dist-info/LICENSE
antchain_ak_c810f9cbf799426aa25d207ce46b7566-1.0.0.dist-info/METADATA
antchain_ak_c810f9cbf799426aa25d207ce46b7566-1.0.0.dist-info/WHEEL
antchain_ak_c810f9cbf799426aa25d207ce46b7566-1.0.0.dist-info/top_level.txt
antchain_ak_c810f9cbf799426aa25d207ce46b7566-1.0.0.dist-info/RECORD
